vivplots/__init__.py
vivplots/layout.py
vivplots/signals.py
vivplots-0.0.7.dist-info/METADATA
vivplots-0.0.7.dist-info/WHEEL
vivplots-0.0.7.dist-info/top_level.txt
vivplots-0.0.7.dist-info/RECORD
