Metadata-Version: 2.1
Name: vivplots
Version: 0.0.7
Summary: Common plotting modules for Vivent
Home-page: https://github.com/vivent-sarl/vivplots
Author: Thomas Meacham
Author-email: thomas.meacham@vivent.ch
License: UNKNOWN
Platform: UNKNOWN
Classifier: Programming Language :: Python :: 3
Classifier: License :: OSI Approved :: MIT License
Classifier: Operating System :: OS Independent
Requires-Dist: numpy (>=1.19.5)
Requires-Dist: pandas (>=1.1.5)
Requires-Dist: plotly (>=5.4.0)
